ska/__init__.py
ska/cache.py
ska/cli.py
ska/filter.py
ska/spectrum.py
ska/svo.py
space_ska-2.0.dist-info/LICENSE
space_ska-2.0.dist-info/METADATA
space_ska-2.0.dist-info/WHEEL
space_ska-2.0.dist-info/entry_points.txt
space_ska-2.0.dist-info/RECORD
